LICENSE
MANIFEST.in
README.md
requirements.txt
setup.cfg
setup.py
src/RemoteTransfer/__init__.py
src/RemoteTransfer/version.py
src/robotframework_remotetransfer_sf.egg-info/PKG-INFO
src/robotframework_remotetransfer_sf.egg-info/SOURCES.txt
src/robotframework_remotetransfer_sf.egg-info/dependency_links.txt
src/robotframework_remotetransfer_sf.egg-info/requires.txt
src/robotframework_remotetransfer_sf.egg-info/top_level.txt