Metadata-Version: 2.1
Name: robotframework-remotetransfer-sf
Version: 0.0.2
Summary: Keyword library to allow transfering screenshots from remoteserver to local machine
Home-page: https://github.com/rasjani/robotframework-remotetransfer
Author: Jani Mikkonen
Author-email: jani.mikkonen@siili.com
License: Apache License 2.0
Keywords: robot framework testing remote file transfer software testing
Platform: any
Classifier: Development Status :: 3 - Alpha
Classifier: Topic :: Software Development :: Testing
Classifier: Operating System :: OS Independent
Classifier: License :: OSI Approved :: Apache Software License
Classifier: Programming Language :: Python
Classifier: Programming Language :: Python :: 3
Classifier: Topic :: Software Development :: Testing
Classifier: Framework :: Robot Framework
Classifier: Framework :: Robot Framework :: Library
